{
  "results": [
    {
      "answers": [
        {
          "questionId": 0,
          "answerId": 1
        },
        {
          "questionId": 1,
          "answerId": 0
        }
      ],
      "test_id": 8,
      "id": 1
    },
    {
      "answers": [
        {
          "questionId": 0,
          "answerId": 1
        },
        {
          "questionId": 1,
          "answerId": 0
        }
      ],
      "test_id": 8,
      "id": 2
    },
    {
      "answers": [],
      "test_id": 1,
      "id": 3
    },
    {
      "answers": [],
      "test_id": 8,
      "id": 4
    },
    {
      "answers": [
        {
          "questionId": null,
          "answerId": null
        },
        {
          "questionId": 2,
          "answerId": 1
        }
      ],
      "test_id": 1,
      "id": 5
    }
  ]
}